{"content":"Astro generates relative asset paths; GitHub Pages project sites (user.github.io/repo) require Astro base config set correctly and all internal links relative without leading slash, else 404s especially on nested routes and custom 404 pages. GitHub Pages filesystem is case-sensitive (Linux) unlike local dev on Windows/Mac, causing links that work locally to 404 in production.","source":"web","provider":"websearch","confidence":"LOW","fetched_at":"2026-07-15T22:52:53.751Z","ttl":86400000,"kind":"web"}
